shippy/__init__.py
shippy/__main__.py
shippy/client.py
shippy/config.py
shippy/constants.py
shippy/exceptions.py
shippy/helper.py
shippy/server_compat_version.py
shippy/version.py
shipper_shippy-2.43.0.dist-info/METADATA
shipper_shippy-2.43.0.dist-info/WHEEL
shipper_shippy-2.43.0.dist-info/entry_points.txt
shipper_shippy-2.43.0.dist-info/top_level.txt
shipper_shippy-2.43.0.dist-info/RECORD
