Metadata-Version: 2.4
Name: shipper-shippy
Version: 2.43.0
Summary: Client-side tool to interface with shipper
Home-page: https://github.com/shipperstack/shipper/tree/master/shippy
Author: Eric Park
Author-email: me@ericswpark.com
Project-URL: Bug Tracker, https://github.com/shipperstack/shipper/issues
Classifier: Programming Language :: Python :: 3
Classifier: License :: OSI Approved :: GNU Affero General Public License v3
Classifier: Operating System :: OS Independent
Requires-Python: >=3.10
Requires-Dist: humanize==4.14.0
Requires-Dist: loguru==0.7.3
Requires-Dist: requests==2.32.5
Requires-Dist: rich==14.2.0
Requires-Dist: semver==3.0.4
Requires-Dist: sentry-sdk==2.45.0
Requires-Dist: setuptools==80.9.0
Dynamic: author
Dynamic: author-email
Dynamic: classifier
Dynamic: description
Dynamic: description-content-type
Dynamic: home-page
Dynamic: project-url
Dynamic: requires-dist
Dynamic: requires-python
Dynamic: summary
